llm_hyperbee.py
llm_hyperbee-0.5.dist-info/LICENSE
llm_hyperbee-0.5.dist-info/METADATA
llm_hyperbee-0.5.dist-info/WHEEL
llm_hyperbee-0.5.dist-info/entry_points.txt
llm_hyperbee-0.5.dist-info/top_level.txt
llm_hyperbee-0.5.dist-info/RECORD
