Metadata-Version: 2.1
Name: llm-hyperbee
Version: 0.5
Summary: Access hyperbee.ai models via API
Author: Cemal Gündüz
License: Apache-2.0
Project-URL: Homepage, https://github.com/HyperbeeAI/llm-hyperbee
Project-URL: Changelog, https://github.com/HyperbeeAI/llm-hyperbee/releases
Project-URL: Issues, https://github.com/HyperbeeAI/llm-hyperbee/issues
Project-URL: CI, https://github.com/HyperbeeAI/llm-hyperbee/actions
Classifier: License :: OSI Approved :: Apache Software License
Requires-Python: >3.7
License-File: LICENSE
Requires-Dist: llm
Provides-Extra: test
Requires-Dist: pytest ; extra == 'test'
